Metadata-Version: 1.1
Name: contra
Version: 0.1.0rc4
Summary: High-performance containers with a Python interface
Home-page: http://github.com/standage/contra
Author: Daniel Standage
Author-email: daniel.standage@gmail.com
License: MIT
Platform: UNKNOWN
Classifier: Development Status :: 4 - Beta
Classifier: Environment :: Console
Classifier: License :: OSI Approved :: MIT License
Classifier: Programming Language :: Python :: 2.7
Classifier: Programming Language :: Python :: 3.4
Classifier: Programming Language :: Python :: 3.5
Classifier: Topic :: Scientific/Engineering :: Bio-Informatics
